{"cameraMode":{"drawMode":0,"name":"Shaded","section":"Shading Mode"},"sceneLighting":true,"audioPlay":false,"sceneViewState":{"showFog":true,"showMaterialUpdate":false,"showSkybox":true,"showFlares":true,"showImageEffects":true,"showParticleSystems":true},"in2DMode":false,"pivot":{"x":-56.552215576171878,"y":98.58897399902344,"z":129.8201904296875},"rotation":{"x":-0.14064979553222657,"y":-0.7333107590675354,"z":0.15980468690395356,"w":-0.6458702683448792},"size":7.129958152770996,"orthographic":false}